aiocasambi/__init__.py
aiocasambi/__main__.py
aiocasambi/__test_network_login__.py
aiocasambi/__test_user_login__.py
aiocasambi/__test_ws_connect.py
aiocasambi/consts.py
aiocasambi/controller.py
aiocasambi/errors.py
aiocasambi/helper.py
aiocasambi/scenes.py
aiocasambi/unit.py
aiocasambi/units.py
aiocasambi/websocket.py
aiocasambi-0.285.dist-info/LICENSE.txt
aiocasambi-0.285.dist-info/METADATA
aiocasambi-0.285.dist-info/WHEEL
aiocasambi-0.285.dist-info/top_level.txt
aiocasambi-0.285.dist-info/RECORD
