Metadata-Version: 2.1
Name: aiocasambi
Version: 0.285
Summary: aio library to control Casambi light through cloudapi
Home-page: https://github.com/hellqvio86/aiocasambi
Download-URL: https://github.com/hellqvio86/aiocasambi/archive/v_01.tar.gz
Author: Olof Hellqvist
Author-email: olof.hellqvist@gmail.com
License: MIT
Keywords: casambi,light
Classifier: Development Status :: 3 - Alpha
Classifier: Intended Audience :: Developers
Classifier: Topic :: Software Development :: Build Tools
Classifier: License :: OSI Approved :: MIT License
Classifier: Programming Language :: Python :: 3
Classifier: Programming Language :: Python :: 3.6
Requires-Python: >=3.6
License-File: LICENSE.txt
Requires-Dist: aiohttp
Requires-Dist: pyyaml
Provides-Extra: tests
Requires-Dist: pyyaml ; extra == 'tests'
